{
  "section": {
    "prefix": "section",
    "description": "Sass section comment.",
    "body": [
      "// ====================================================================",
      "// $1",
      "// ===================================================================="
    ]
  },

  "subsection": {
    "prefix": "subsection",
    "description": "Sass subsection comment.",
    "body": [
      "//",
      "// $1",
      "// ===================================================================="
    ]
  }
}
